cz_kpn/__init__.py
cz_kpn/consts.py
cz_kpn/cz_kpn_info.txt
cz_kpn/rules.py
cz_kpn-4.1.0.dist-info/METADATA
cz_kpn-4.1.0.dist-info/WHEEL
cz_kpn-4.1.0.dist-info/entry_points.txt
cz_kpn-4.1.0.dist-info/licenses/LICENSE
cz_kpn-4.1.0.dist-info/RECORD
