Metadata-Version: 2.4
Name: cz-kpn
Version: 4.1.0
Summary: commitizen with kpn style
License-Expression: MIT
License-File: LICENSE
Keywords: commitizen,release-management,autorelease
Author: Santiago Fraire Willemoes
Author-email: santiago.frairewillemoes@kpn.com
Requires-Python: >=3.10,<4.0
Classifier: Operating System :: OS Independent
Classifier: Programming Language :: Python :: 3
Classifier: Programming Language :: Python :: 3.10
Classifier: Programming Language :: Python :: 3.11
Classifier: Programming Language :: Python :: 3.12
Classifier: Programming Language :: Python :: 3.13
Classifier: Programming Language :: Python :: 3.14
Classifier: Topic :: Software Development :: Build Tools
Classifier: Topic :: Software Development :: Libraries :: Python Modules
Requires-Dist: commitizen (>=3.29.0,<5.0.0)
Project-URL: Repository, https://github.com/kpn/cz-kpn
